{ "compressionlevel":-1,
 "height":15,
 "infinite":false,
 "layers":[
        {
         "data":[157, 157, 157, 157, 157, 157, 157, 157, 157, 157, 157, 157, 157, 157, 157,
            157, 157, 157, 157, 157, 157, 157, 157, 157, 157, 157, 157, 157, 157, 157,
            157, 157, 157, 157, 157, 157, 157, 157, 157, 157, 157, 157, 157, 157, 157,
            157, 157, 157, 157, 157, 157, 157, 157, 157, 157, 157, 157, 157, 157, 157,
            157, 157, 157, 157, 157, 157, 157, 157, 157, 157, 157, 157, 157, 157, 157,
            157, 157, 157, 157, 157, 157, 157, 157, 157, 157, 157, 157, 157, 157, 157,
            157, 157, 157, 157, 157, 157, 157, 157, 157, 157, 157, 157, 157, 157, 157,
            157, 157, 157, 157, 157, 157, 157, 157, 157, 157, 157, 157, 157, 157, 157,
            157, 157, 157, 157, 157, 157, 157, 157, 157, 157, 157, 157, 157, 157, 157,
            157, 157, 157, 157, 157, 157, 157, 157, 157, 157, 157, 157, 157, 157, 157,
            157, 157, 157, 157, 157, 157, 157, 157, 157, 157, 157, 157, 157, 157, 157,
            157, 157, 157, 157, 157, 157, 157, 157, 157, 157, 157, 157, 157, 157, 157,
            157, 157, 157, 157, 157, 157, 157, 157, 157, 157, 157, 157, 157, 157, 157,
            157, 157, 157, 157, 157, 157, 157, 157, 157, 157, 157, 157, 157, 157, 157,
            157, 157, 157, 157, 157, 157, 157, 157, 157, 157, 157, 157, 157, 157, 157],
         "height":15,
         "id":1,
         "name":"ground",
         "opacity":1,
         "type":"tilelayer",
         "visible":true,
         "width":15,
         "x":0,
         "y":0
        }, 
        {
         "data":[171, 171, 171, 171, 171, 171, 171, 171, 171, 171, 171, 171, 171, 171, 171,
            171, 0, 0, 0, 0, 0, 0, 0, 0, 0, 0, 0, 0, 0, 171,
            171, 0, 0, 0, 0, 0, 0, 0, 0, 0, 0, 0, 0, 0, 171,
            171, 0, 0, 0, 0, 0, 0, 0, 0, 0, 171, 0, 0, 0, 171,
            171, 171, 171, 171, 171, 171, 171, 171, 171, 171, 171, 0, 0, 0, 171,
            171, 0, 0, 0, 0, 0, 0, 0, 0, 0, 0, 0, 0, 0, 171,
            171, 0, 0, 0, 0, 0, 0, 0, 0, 0, 0, 0, 0, 0, 171,
            171, 0, 0, 171, 171, 171, 171, 171, 171, 171, 171, 171, 171, 171, 171,
            171, 0, 0, 171, 0, 0, 0, 0, 0, 0, 0, 0, 0, 0, 171,
            171, 0, 0, 0, 0, 0, 0, 0, 0, 0, 0, 0, 0, 0, 171,
            171, 0, 0, 0, 0, 0, 0, 0, 0, 0, 0, 0, 0, 0, 171,
            171, 171, 171, 171, 171, 171, 171, 171, 171, 171, 171, 0, 0, 0, 171,
            171, 0, 0, 0, 0, 0, 0, 0, 0, 0, 0, 0, 0, 0, 171,
            171, 0, 0, 0, 0, 0, 0, 0, 0, 0, 0, 0, 0, 0, 171,
            171, 171, 171, 171, 171, 171, 171, 171, 171, 171, 171, 171, 171, 171, 171],
         "height":15,
         "id":2,
         "name":"walls",
         "opacity":1,
         "type":"tilelayer",
         "visible":true,
         "width":15,
         "x":0,
         "y":0
        }, 
        {
         "data":[0, 0, 0, 0, 0, 0, 0, 0, 0, 0, 0, 0, 0, 0, 0,
            0, 159, 0, 0, 0, 0, 0, 0, 0, 0, 0, 0, 0, 0, 0,
            0, 0, 29, 0, 0, 0, 5, 0, 0, 0, 0, 0, 0, 0, 0,
            0, 0, 0, 0, 0, 0, 0, 0, 0, 0, 0, 0, 0, 0, 0,
            0, 0, 0, 0, 0, 0, 0, 0, 0, 0, 0, 0, 0, 0, 0,
            0, 0, 0, 0, 0, 0, 0, 0, 0, 3, 0, 0, 0, 0, 0,
            0, 0, 0, 0, 0, 0, 0, 0, 0, 0, 0, 0, 0, 0, 0,
            0, 0, 0, 0, 0, 0, 0, 0, 0, 0, 0, 0, 0, 0, 0,
            0, 0, 0, 0, 0, 0, 0, 0, 0, 0, 0, 0, 0, 0, 0,
            0, 0, 0, 0, 0, 0, 0, 0, 0, 0, 0, 0, 0, 0, 0,
            0, 0, 0, 1, 0, 0, 0, 0, 0, 0, 0, 0, 0, 0, 0,
            0, 0, 0, 0, 0, 0, 0, 0, 0, 0, 0, 0, 0, 0, 0,
            0, 0, 0, 0, 0, 0, 0, 0, 0, 0, 0, 0, 0, 0, 0,
            0, 0, 0, 0, 0, 0, 0, 0, 0, 0, 0, 0, 0, 0, 0,
            0, 0, 0, 0, 0, 0, 0, 0, 0, 0, 0, 0, 0, 0, 0],
         "height":15,
         "id":4,
         "name":"objects_entity",
         "opacity":1,
         "type":"tilelayer",
         "visible":true,
         "width":15,
         "x":0,
         "y":0
        }, 
        {
         "draworder":"topdown",
         "id":5,
         "name":"objects",
         "objects":[
                {
                 "height":44.4444444444445,
                 "id":18,
                 "name":"",
                 "properties":[
                        {
                         "name":"basic_atk",
                         "type":"int",
                         "value":2
                        }, 
                        {
                         "name":"basic_hp",
                         "type":"int",
                         "value":10
                        }, 
                        {
                         "name":"kind",
                         "type":"string",
                         "value":"monster"
                        }, 
                        {
                         "name":"name",
                         "type":"string",
                         "value":"Slime"
                        }],
                 "rotation":0,
                 "type":"",
                 "visible":true,
                 "width":46.6666666666667,
                 "x":145.555555555556,
                 "y":482.222222222222
                }, 
                {
                 "height":44.4444,
                 "id":19,
                 "name":"",
                 "properties":[
                        {
                         "name":"basic_atk",
                         "type":"int",
                         "value":2
                        }, 
                        {
                         "name":"basic_hp",
                         "type":"int",
                         "value":10
                        }, 
                        {
                         "name":"kind",
                         "type":"string",
                         "value":"monster"
                        }, 
                        {
                         "name":"name",
                         "type":"string",
                         "value":"Slime"
                        }],
                 "rotation":0,
                 "type":"",
                 "visible":true,
                 "width":46.6667,
                 "x":431.111094444444,
                 "y":240.000022222222
                }, 
                {
                 "height":44.4444,
                 "id":20,
                 "name":"",
                 "properties":[
                        {
                         "name":"basic_atk",
                         "type":"int",
                         "value":2
                        }, 
                        {
                         "name":"basic_hp",
                         "type":"int",
                         "value":10
                        }, 
                        {
                         "name":"kind",
                         "type":"string",
                         "value":"monster"
                        }, 
                        {
                         "name":"name",
                         "type":"string",
                         "value":"Slime"
                        }],
                 "rotation":0,
                 "type":"",
                 "visible":true,
                 "width":46.6667,
                 "x":287.777761111111,
                 "y":96.6666888888889
                }, 
                {
                 "height":53.3332888888889,
                 "id":21,
                 "name":"",
                 "properties":[
                        {
                         "name":"basic_atk",
                         "type":"int",
                         "value":2
                        }, 
                        {
                         "name":"basic_hp",
                         "type":"int",
                         "value":10
                        }, 
                        {
                         "name":"kind",
                         "type":"string",
                         "value":"monster"
                        }, 
                        {
                         "name":"name",
                         "type":"string",
                         "value":"Skeleton"
                        }],
                 "rotation":0,
                 "type":"",
                 "visible":true,
                 "width":62.2222555555555,
                 "x":88.8888722222222,
                 "y":96.6666888888889
                }, 
                {
                 "height":46.6667,
                 "id":23,
                 "name":"",
                 "properties":[
                        {
                         "name":"kind",
                         "type":"string",
                         "value":"player"
                        }],
                 "rotation":0,
                 "type":"",
                 "visible":true,
                 "width":45.3333,
                 "x":51.7777944444445,
                 "y":621.111094444444
                }, 
                {
                 "height":42.6667,
                 "id":24,
                 "name":"",
                 "properties":[
                        {
                         "name":"kind",
                         "type":"string",
                         "value":"stairs"
                        }],
                 "rotation":0,
                 "type":"",
                 "visible":true,
                 "width":46.6667,
                 "x":47.7777611111111,
                 "y":51.9999833333333
                }],
         "opacity":1,
         "type":"objectgroup",
         "visible":true,
         "x":0,
         "y":0
        }],
 "nextlayerid":6,
 "nextobjectid":25,
 "orientation":"orthogonal",
 "renderorder":"right-down",
 "tiledversion":"1.11.2",
 "tileheight":48,
 "tilesets":[
        {
         "columns":13,
         "firstgid":1,
         "image":"..\/..\/map_editor\/tiles\/sprite.png",
         "imageheight":672,
         "imagewidth":624,
         "margin":0,
         "name":"sprite",
         "spacing":0,
         "tilecount":182,
         "tileheight":48,
         "tiles":[
                {
                 "id":8,
                 "properties":[
                        {
                         "name":"kind",
                         "type":"string",
                         "value":"mentor"
                        }]
                }, 
                {
                 "id":9,
                 "properties":[
                        {
                         "name":"kind",
                         "type":"string",
                         "value":"mentor"
                        }]
                }, 
                {
                 "id":112,
                 "properties":[
                        {
                         "name":"kind",
                         "type":"string",
                         "value":"item"
                        }, 
                        {
                         "name":"name",
                         "type":"string",
                         "value":"wing"
                        }]
                }, 
                {
                 "id":113,
                 "properties":[
                        {
                         "name":"kind",
                         "type":"string",
                         "value":"item"
                        }, 
                        {
                         "name":"name",
                         "type":"string",
                         "value":"wing"
                        }]
                }, 
                {
                 "id":117,
                 "properties":[
                        {
                         "name":"dir",
                         "type":"string",
                         "value":"down"
                        }, 
                        {
                         "name":"kind",
                         "type":"string",
                         "value":"player"
                        }, 
                        {
                         "name":"seq",
                         "type":"string",
                         "value":"0"
                        }]
                }, 
                {
                 "id":118,
                 "properties":[
                        {
                         "name":"dir",
                         "type":"string",
                         "value":"down"
                        }, 
                        {
                         "name":"kind",
                         "type":"string",
                         "value":"player"
                        }, 
                        {
                         "name":"seq",
                         "type":"string",
                         "value":"1"
                        }]
                }, 
                {
                 "id":119,
                 "properties":[
                        {
                         "name":"dir",
                         "type":"string",
                         "value":"default"
                        }, 
                        {
                         "name":"kind",
                         "type":"string",
                         "value":"player"
                        }]
                }, 
                {
                 "id":120,
                 "properties":[
                        {
                         "name":"dir",
                         "type":"string",
                         "value":"up"
                        }, 
                        {
                         "name":"kind",
                         "type":"string",
                         "value":"player"
                        }, 
                        {
                         "name":"seq",
                         "type":"string",
                         "value":"0"
                        }]
                }, 
                {
                 "id":121,
                 "properties":[
                        {
                         "name":"dir",
                         "type":"string",
                         "value":"up"
                        }, 
                        {
                         "name":"kind",
                         "type":"string",
                         "value":"player"
                        }, 
                        {
                         "name":"seq",
                         "type":"string",
                         "value":"1"
                        }]
                }, 
                {
                 "id":122,
                 "properties":[
                        {
                         "name":"dir",
                         "type":"string",
                         "value":"left"
                        }, 
                        {
                         "name":"kind",
                         "type":"string",
                         "value":"player"
                        }, 
                        {
                         "name":"seq",
                         "type":"string",
                         "value":"0"
                        }]
                }, 
                {
                 "id":123,
                 "properties":[
                        {
                         "name":"dir",
                         "type":"string",
                         "value":"left"
                        }, 
                        {
                         "name":"kind",
                         "type":"string",
                         "value":"player"
                        }, 
                        {
                         "name":"seq",
                         "type":"string",
                         "value":"1"
                        }]
                }, 
                {
                 "id":124,
                 "properties":[
                        {
                         "name":"dir",
                         "type":"string",
                         "value":"right"
                        }, 
                        {
                         "name":"kind",
                         "type":"string",
                         "value":"player"
                        }, 
                        {
                         "name":"seq",
                         "type":"string",
                         "value":"0"
                        }]
                }, 
                {
                 "id":125,
                 "properties":[
                        {
                         "name":"dir",
                         "type":"string",
                         "value":"right"
                        }, 
                        {
                         "name":"kind",
                         "type":"string",
                         "value":"player"
                        }, 
                        {
                         "name":"seq",
                         "type":"string",
                         "value":"1"
                        }]
                }, 
                {
                 "id":130,
                 "properties":[
                        {
                         "name":"kind",
                         "type":"string",
                         "value":"item"
                        }, 
                        {
                         "name":"name",
                         "type":"string",
                         "value":"sword"
                        }]
                }, 
                {
                 "id":131,
                 "properties":[
                        {
                         "name":"kind",
                         "type":"string",
                         "value":"item"
                        }, 
                        {
                         "name":"name",
                         "type":"string",
                         "value":"sword"
                        }]
                },
            
                {
                 "id":132,
                 "properties":[
                        {
                         "name":"kind",
                         "type":"string",
                         "value":"item"
                        }, 
                        {
                         "name":"name",
                         "type":"string",
                         "value":"sword"
                        }]
                }, 
                {
                 "id":133,
                 "properties":[
                        {
                         "name":"kind",
                         "type":"string",
                         "value":"item"
                        }, 
                        {
                         "name":"name",
                         "type":"string",
                         "value":"sword"
                        }]
                }, 
                {
                 "id":134,
                 "properties":[
                        {
                         "name":"kind",
                         "type":"string",
                         "value":"item"
                        }, 
                        {
                         "name":"name",
                         "type":"string",
                         "value":"sword"
                        }]
                }, 
                {
                 "id":135,
                 "properties":[
                        {
                         "name":"color",
                         "type":"string",
                         "value":"green"
                        }, 
                        {
                         "name":"gid",
                         "type":"string",
                         "value":"key_green"
                        }, 
                        {
                         "name":"kind",
                         "type":"string",
                         "value":"key"
                        }, 
                        {
                         "name":"name",
                         "type":"string",
                         "value":"green key"
                        }]
                }, 
                {
                 "id":136,
                 "properties":[
                        {
                         "name":"color",
                         "type":"string",
                         "value":"blue"
                        }, 
                        {
                         "name":"gid",
                         "type":"string",
                         "value":"key_blue"
                        }, 
                        {
                         "name":"kind",
                         "type":"string",
                         "value":"key"
                        }, 
                        {
                         "name":"name",
                         "type":"string",
                         "value":"blue key"
                        }]
                }, 
                {
                 "id":137,
                 "properties":[
                        {
                         "name":"color",
                         "type":"string",
                         "value":"red"
                        }, 
                        {
                         "name":"gid",
                         "type":"string",
                         "value":"key_red"
                        }, 
                        {
                         "name":"kind",
                         "type":"string",
                         "value":"key"
                        }, 
                        {
                         "name":"name",
                         "type":"string",
                         "value":"red key"
                        }]
                }, 
                {
                 "id":143,
                 "properties":[
                        {
                         "name":"kind",
                         "type":"string",
                         "value":"item"
                        }, 
                        {
                         "name":"name",
                         "type":"string",
                         "value":"shield"
                        }]
                }, 
                {
                 "id":144,
                 "properties":[
                        {
                         "name":"kind",
                         "type":"string",
                         "value":"item"
                        }, 
                        {
                         "name":"name",
                         "type":"string",
                         "value":"shield"
                        }]
                }, 
                {
                 "id":145,
                 "properties":[
                        {
                         "name":"kind",
                         "type":"string",
                         "value":"item"
                        }, 
                        {
                         "name":"name",
                         "type":"string",
                         "value":"shield"
                        }]
                }, 
                {
                 "id":146,
                 "properties":[
                        {
                         "name":"kind",
                         "type":"string",
                         "value":"item"
                        }, 
                        {
                         "name":"name",
                         "type":"string",
                         "value":"shield"
                        }]
                }, 
                {
                 "id":147,
                 "properties":[
                        {
                         "name":"kind",
                         "type":"string",
                         "value":"item"
                        }, 
                        {
                         "name":"name",
                         "type":"string",
                         "value":"shield"
                        }]
                }, 
                {
                 "id":148,
                 "properties":[
                        {
                         "name":"color",
                         "type":"string",
                         "value":"yellow"
                        }, 
                        {
                         "name":"kind",
                         "type":"string",
                         "value":"door"
                        }]
                }, 
                {
                 "id":149,
                 "properties":[
                        {
                         "name":"color",
                         "type":"string",
                         "value":"blue"
                        }, 
                        {
                         "name":"kind",
                         "type":"string",
                         "value":"door"
                        }]
                }, 
                {
                 "id":150,
                 "properties":[
                        {
                         "name":"color",
                         "type":"string",
                         "value":"red"
                        }, 
                        {
                         "name":"kind",
                         "type":"string",
                         "value":"door"
                        }]
                }, 
                {
                 "id":157,
                 "properties":[
                        {
                         "name":"dir",
                         "type":"string",
                         "value":"down"
                        }, 
                        {
                         "name":"kind",
                         "type":"string",
                         "value":"stairs"
                        }]
                },
            
                {
                 "id":158,
                 "properties":[
                        {
                         "name":"dir",
                         "type":"string",
                         "value":"up"
                        }, 
                        {
                         "name":"kind",
                         "type":"string",
                         "value":"stairs"
                        }]
                }, 
                {
                 "id":162,
                 "properties":[
                        {
                         "name":"color",
                         "type":"string",
                         "value":"blue"
                        }, 
                        {
                         "name":"kind",
                         "type":"string",
                         "value":"item"
                        }, 
                        {
                         "name":"name",
                         "type":"string",
                         "value":"diamond"
                        }]
                }, 
                {
                 "id":163,
                 "properties":[
                        {
                         "name":"color",
                         "type":"string",
                         "value":"red"
                        }, 
                        {
                         "name":"kind",
                         "type":"string",
                         "value":"item"
                        }, 
                        {
                         "name":"name",
                         "type":"string",
                         "value":"diamond"
                        }]
                }, 
                {
                 "id":175,
                 "properties":[
                        {
                         "name":"kind",
                         "type":"string",
                         "value":"item"
                        }]
                }, 
                {
                 "id":176,
                 "properties":[
                        {
                         "name":"kind",
                         "type":"string",
                         "value":"item"
                        }]
                }],
         "tilewidth":48
        }],
 "tilewidth":48,
 "type":"map",
 "version":"1.10",
 "width":15
}